crawlers/__init__.py
crawlers/base.py
crawlers/chdbits.py
crawlers/exceptions.py
crawlers/fsm.py
crawlers/mteam.py
crawlers/session.py
jmm-1.0.0.dist-info/LICENSE
jmm-1.0.0.dist-info/METADATA
jmm-1.0.0.dist-info/WHEEL
jmm-1.0.0.dist-info/top_level.txt
jmm-1.0.0.dist-info/RECORD
