Metadata-Version: 2.1
Name: jmm
Version: 1.0.0
Summary: a group of crawlers for private tracker website
Home-page: https://github.com/zqmillet/pt-crawler
Author: kinopico
Author-email: zqmillet@qq.com
License: UNKNOWN
Platform: UNKNOWN
License-File: LICENSE
Requires-Dist: lxml (==4.8.0)
Requires-Dist: pydantic (==1.9.0)
Requires-Dist: requests (==2.25.1)
